aipo/__init__.py
aipo/__main__.py
aipo/app.py
aipo/broker.py
aipo/config.py
aipo/events.py
aipo/message.py
aipo/serializers.py
aipo/task.py
aipo/utils.py
aipo/worker.py
aipo/backends/__init__.py
aipo/backends/redis.py
aipo-0.1.2.dist-info/LICENSE
aipo-0.1.2.dist-info/METADATA
aipo-0.1.2.dist-info/WHEEL
aipo-0.1.2.dist-info/entry_points.txt
aipo-0.1.2.dist-info/top_level.txt
aipo-0.1.2.dist-info/RECORD
