Metadata-Version: 2.1
Name: aipo
Version: 0.1.2
Summary: Aipo is a small and simple asyncio task/job queue.
Home-page: https://github.com/CaiqueReinhold/aipo
Author: Caique Reinhold
Author-email: caiquereinhold@gmail.com
License: BSD
Keywords: asyncio task job queue
Platform: any
Classifier: Development Status :: 2 - Pre-Alpha
Classifier: License :: OSI Approved :: BSD License
Classifier: Programming Language :: Python :: 3 :: Only
Classifier: Programming Language :: Python :: 3.10
Classifier: Programming Language :: Python :: 3.11
Classifier: Programming Language :: Python :: Implementation :: CPython
Classifier: Operating System :: POSIX
Classifier: Operating System :: Unix
Classifier: Environment :: No Input/Output (Daemon)
Classifier: Framework :: AsyncIO
Classifier: Intended Audience :: Developers
Requires-Python: >=3.8
License-File: LICENSE
Requires-Dist: pyyaml (>=6.0)
Provides-Extra: redis
Requires-Dist: redis (>=4.4.0) ; extra == 'redis'
Provides-Extra: uvloop
Requires-Dist: uvloop (>=0.8.1) ; extra == 'uvloop'
